LICENSE
ossindex/__init__.py
ossindex/exception.py
ossindex/model.py
ossindex/ossindex.py
ossindex/py.typed
ossindex/serializer.py
ossindex_lib-1.1.1.dist-info/LICENSE
ossindex_lib-1.1.1.dist-info/WHEEL
ossindex_lib-1.1.1.dist-info/METADATA
ossindex_lib-1.1.1.dist-info/RECORD
