Metadata-Version: 2.1
Name: ossindex-lib
Version: 1.1.1
Summary: A library for querying the OSS Index free catalogue of open source components to help developers identify vulnerabilities, understand risk, and keep their software safe.
Home-page: https://github.com/sonatype-nexus-community/ossindex-python
License: Apache-2.0
Keywords: SCA,OWASP
Author: Paul Horton
Author-email: phorton@sonatype.com
Maintainer: Paul Horton
Maintainer-email: phorton@sonatype.com
Requires-Python: >=3.6,<4.0
Classifier: Development Status :: 5 - Production/Stable
Classifier: Intended Audience :: Developers
Classifier: Intended Audience :: Information Technology
Classifier: Intended Audience :: Legal Industry
Classifier: Intended Audience :: System Administrators
Classifier: License :: OSI Approved :: Apache Software License
Classifier: Programming Language :: Python :: 3
Classifier: Programming Language :: Python :: 3.10
Classifier: Programming Language :: Python :: 3.6
Classifier: Programming Language :: Python :: 3.7
Classifier: Programming Language :: Python :: 3.8
Classifier: Programming Language :: Python :: 3.9
Classifier: Topic :: Security
Classifier: Topic :: Software Development
Classifier: Topic :: System :: Software Distribution
Classifier: Typing :: Typed
Requires-Dist: PyYAML (>=5.4.1,<7.0.0)
Requires-Dist: importlib-metadata (>=3.4); python_version < "3.8"
Requires-Dist: packageurl-python (>=0.9.0,<0.10.0)
Requires-Dist: requests (>=2.20.0,<3.0.0)
Requires-Dist: tinydb (>=4.5.0,<5.0.0)
Requires-Dist: types-PyYAML (>=5.4.1,<6.0.0)
Requires-Dist: types-requests (>=2.25.1,<3.0.0)
Requires-Dist: types-setuptools (>=57.0.0)
Project-URL: Bug Tracker, https://github.com/sonatype-nexus-community/ossindex-python/issues
Project-URL: Repository, https://github.com/sonatype-nexus-community/ossindex-python
